{
  "__comment__": "This file was automatically created by mcresources",
  "variants": {
    "": [
      {
        "model": "terrafabricraft:block/wood/fallen_leaves/sequoia",
        "y": 90
      },
      {
        "model": "terrafabricraft:block/wood/fallen_leaves/sequoia"
      },
      {
        "model": "terrafabricraft:block/wood/fallen_leaves/sequoia",
        "y": 180
      },
      {
        "model": "terrafabricraft:block/wood/fallen_leaves/sequoia",
        "y": 270
      }
    ]
  }
}